[{"id":10,"name":"Dr. Lluch - Mare de Déu del Sufragi"},{"id":1007,"name":"Jesús Morante Borràs (I)"},{"id":1008,"name":"Jesús Morante Borràs (II)"},{"id":1009,"name":"Jesús Morante Borràs (III)"},{"id":1010,"name":"Jesús Morante Borràs (IV)"},{"id":1011,"name":"Jesús Morante Borràs (V)"},{"id":1012,"name":"Jesús Morante Borràs (VI)"},{"id":1013,"name":"Jesús Morante Borràs (VII)"},{"id":1014,"name":"Jesús Morante Borràs (VIII)"},{"id":1015,"name":"Jesús Morante Borràs (IX)"},{"id":1016,"name":"Jesús Morante Borràs (X)"},{"id":1020,"name":"Albereda - Passarel.la de l'Exposició"},{"id":1021,"name":"Albereda - Pla del Real"},{"id":1024,"name":"Palau de Justícia - Glorieta"},{"id":1026,"name":"Ribàs (impar) - Ador"},{"id":1027,"name":"Principal - El Caroig"},{"id":1028,"name":"Mare de Déu de Lepant (impar) - Esc. F. Siurana"},{"id":1029,"name":"Vicent Puchol - Font de Bonet"},{"id":1030,"name":"Crist del Refugi - Davant Sant Agustí"},{"id":1032,"name":"Tírig - Guàrdia Civil"},{"id":1034,"name":"Cerdà de Tallada - Colón"},{"id":1035,"name":"Aragó - Finlàndia"},{"id":1036,"name":"Uruguai - Veneçuela"},{"id":1038,"name":"Arxiduc Carles (impar) - Tres Forques"},{"id":1039,"name":"Ernest Ferrer - Aragó"},{"id":1041,"name":"Ramón i Cajal - Pintor Benedito"},{"id":1042,"name":"Regne de València - Ciscar"},{"id":1044,"name":"Vicent Andrés Estellés - Poliesportiu"},{"id":1050,"name":"Mediterránia - Vicent Brull"},{"id":1052,"name":"Eugènia Viñes - Mare de Déu del Sufragi"},{"id":1054,"name":"Aragó - Saragossa"},{"id":1055,"name":"Aragó - Ernest Ferrer"},{"id":1057,"name":"Aragó - Blasco Ibáñez"},{"id":1060,"name":"Pere Cabanes - Mont Carmel"},{"id":1061,"name":"Pere Cabanes - Sant Doménec Savio"},{"id":1062,"name":"Pere Cabanes - Bisbe Laguarda"},{"id":1067,"name":"Equador - Pintor Matarana"},{"id":1080,"name":"Sant Vicent de Paül - Peñíscola"},{"id":1083,"name":"Aragó - Amadeu de Savoia"},{"id":1085,"name":"Aragó - Xile"},{"id":1087,"name":"Sant Antoni - Pizarro"},{"id":1091,"name":"Malilla (par) - Bernat Descoll"},{"id":1096,"name":"Ramon Llull - Bernat Fenollar"},{"id":11,"name":"Dr. Lluch - Pescadors"},{"id":1109,"name":"Tomàs Montañana (impar) - Astúries"},{"id":1110,"name":"Dr. Manuel Candela (par) - Port"},{"id":1111,"name":"Dr. Manuel Candela (par) - Sants Just i Pastor"},{"id":1114,"name":"Ramon Llull - García Donato"},{"id":1116,"name":"Dr. Manuel Candela (impar) - Blasco Ibáñez"},{"id":1117,"name":"Dr. Manuel Candela (impar) - Sants Just i Pastor"},{"id":1118,"name":"Dr. Manuel Candela (impar) - Rodríguez de Cepeda"},{"id":1119,"name":"Dr. Manuel Candela (impar) - Port"},{"id":112,"name":"Ramon Llull - Leandro de Saralegui"},{"id":1120,"name":"Tomàs Montañana (par) - Astúries"},{"id":1125,"name":"Comte de Torrefiel - Mestre Marçal"},{"id":1126,"name":"Comte de Torrefiel - Josep Esteve"},{"id":1127,"name":"Comte de Torrefiel - Riu Bidasoa"},{"id":1128,"name":"Sant Doménec Savio - Alemany"},{"id":1129,"name":"Sant Doménec Savio - Josep Esteve"},{"id":113,"name":"Blasco Ibáñez - Ramon Llull"},{"id":1130,"name":"Pere Patrici Mey - Felip Rinaldi"},{"id":1131,"name":"Pintor Jacomart - Comte de Torrefiel"},{"id":1132,"name":"Músic Espí - Gravador Fabregat"},{"id":1133,"name":"Comte de Lumiares - Tossal del Rei"},{"id":1134,"name":"Blasco Ibáñez (par) - José María Haro"},{"id":1136,"name":"Palma de Gandia - Venta del Moro"},{"id":1137,"name":"Ferrer i Bigné - Aiacor"},{"id":1138,"name":"Ferrer i Bigné - Santíssima Creu"},{"id":1139,"name":"Ferrer i Bigné - Nelo el Fariner"},{"id":114,"name":"Blasco Ibáñez - Vinalopó"},{"id":1140,"name":"Camí de Montcada - Gasolinera"},{"id":1141,"name":"Germans Maristes (impar) - Fonteta Sant Lluís"},{"id":1143,"name":"Gravador Jordán - Músic Cuesta"},{"id":1145,"name":"Vicent Andrés Estellés - Facultat de Farmàcia"},{"id":1148,"name":"Font d'en Corts (impar) - Alqueria Reial"},{"id":1149,"name":"Font d'en Corts (par) - Davant Alqueria Reial"},{"id":115,"name":"Blasco Ibáñez - República Argentina"},{"id":1150,"name":"Pintor Jacomart - Sant Doménec Savio"},{"id":1151,"name":"Comte de Lumiares - Falcons"},{"id":1152,"name":"Camí de Montcada - Camí Alqueria de Marquet"},{"id":1153,"name":"Polvorí - Cullera"},{"id":1154,"name":"Eugènia Viñes (par) - Marcos Sopena"},{"id":1156,"name":"Pavia - Platja de les Arenes"},{"id":1157,"name":"Pavia - Platja de la Malva-rosa"},{"id":1158,"name":"Passeig Marítim - Séquia de la Cadena"},{"id":1159,"name":"Passeig Marítim - Riu Tajo"},{"id":116,"name":"Blasco Ibáñez - Dr. Manuel Candela"},{"id":1160,"name":"Passeig Marítim - Vicent la Roda"},{"id":1161,"name":"Passeig Marítim - Font d'en Carrós"},{"id":1162,"name":"Passeig Marítim - Mendizábal"},{"id":1163,"name":"Isabel de Villena - Font d'en Carrós"},{"id":1164,"name":"Isabel de Villena - Vicent la Roda"},{"id":1165,"name":"Isabel de Villena - Riu Tajo"},{"id":1167,"name":"Eugènia Viñes (impar) - Marcos Sopena"},{"id":1168,"name":"Marcos Sopena - Armada Espanyola"},{"id":117,"name":"Ramon Llull - Escultor Alfons Gabino"},{"id":1170,"name":"Foc - Amadeu Desfilis"},{"id":1175,"name":"Tres Creus - Segona República Espanyola"},{"id":1176,"name":"Tres Creus - Dr. Pérez Feliu"},{"id":1177,"name":"Tres Creus - Tres Forques"},{"id":1183,"name":"General Avilés (par) - Dr. Nicasi Benlloch"},{"id":1184,"name":"General Avilés - Miguel Servet (par)"},{"id":1190,"name":"Tres Creus - dels Hostalers"},{"id":1199,"name":"Comte de Torrefiel - Escultor Piquer"},{"id":12,"name":"Dr. Lluch - Pintor Ferrandis"},{"id":1210,"name":"Blasco Ibáñez - Serradora"},{"id":1211,"name":"Blasco Ibáñez (impar) - José María Haro"},{"id":1217,"name":"Dr. Peset Aleixandre - Felip Rinaldi"},{"id":1218,"name":"Amadeu de Savoia - Muñoz Seca"},{"id":1220,"name":"Marie Curie- Molí de Serra"},{"id":1223,"name":"Tres Creus (carril bus) - Pare Esteban Pernet"},{"id":1225,"name":"Camí nou de Picanya - Arquitecte Segura de Lago"},{"id":1229,"name":"Santiago Rusiñol - Sant Joan Bosco"},{"id":1231,"name":"Dolores Marqués - Benicarló"},{"id":1232,"name":"Dolores Marqués - Reverend José María Pinazo"},{"id":1233,"name":"Dolores Marqués - Assagador d'Alboraia"},{"id":1239,"name":"Primat Reig - Xàbia"},{"id":124,"name":"Blasco Ibáñez - José María Orense"},{"id":1240,"name":"Lliri Blau - Mestre Ventura Pascual"},{"id":1241,"name":"Blasco Ibáñez - Dr. Moliner"},{"id":1242,"name":"Mediterrània - Dr. Lluch"},{"id":1243,"name":"Mediterrània - Reina"},{"id":1245,"name":"Albereda - Armando Palacio Valdés"},{"id":125,"name":"Blasco Ibáñez - Actor Enrique Rambal"},{"id":1252,"name":"Pl. de l'Ajuntament - Sang"},{"id":1254,"name":"Cid - Aiora"},{"id":126,"name":"Blasco Ibáñez - Hondures"},{"id":1261,"name":"Pau - Bonaire"},{"id":1262,"name":"Sorní - Comte de Salvatierra"},{"id":1263,"name":"Comte de Salvatierra - Colón"},{"id":1265,"name":"Campanar (par) - la Fe"},{"id":1266,"name":"Campanar (impar) - la Fe"},{"id":1268,"name":"Tres Creus - Hospital"},{"id":127,"name":"Blasco Ibáñez - Actriu Encarna Máñez"},{"id":1272,"name":"Pius XII (impar) - Monestir de Poblet"},{"id":1274,"name":"Tres Creus - Rei Saud"},{"id":1277,"name":"Primat Reig - Ministre Luis Mayans"},{"id":1278,"name":"Àngel Guimerà - Ferran el Catòlic"},{"id":1279,"name":"Eugènia Viñes - Passeig de Neptú"},{"id":128,"name":"Blasco Ibáñez - Músic Ginés"},{"id":1280,"name":"Pintor Jacomart - Alcanyís"},{"id":1282,"name":"Ramon Llull - Albalat dels Tarongers"},{"id":1283,"name":"Ramon Llull - Campus Tarongers"},{"id":1289,"name":"Vicent Puchol - Arbres"},{"id":129,"name":"Blasco Ibáñez - Enginyer Rafael Janini"},{"id":1290,"name":"Vicent Puchol - Carrera dels Bales"},{"id":1295,"name":"Mestre Rodrigo - Marqués de Sant Joan"},{"id":1296,"name":"Marqués de Sant Joan - Campanar"},{"id":1298,"name":"Espinosa - Ferran el Catòlic"},{"id":1299,"name":"Guillem Sorolla - Torn de l'Hospital"},{"id":13,"name":"Dr. Lluch - Vicent Guillot"},{"id":1300,"name":"Editor Manuel Aguilar - Av. de l'Oest"},{"id":1305,"name":"Guillem de Castro - Lliria"},{"id":1306,"name":"Manuel Soto Enginyer (impar) - Pont de les Drassanes"},{"id":1307,"name":"Tres Creus - Llombai"},{"id":1310,"name":"Manuel Carboneres - Sant Francesc de Paula"},{"id":1311,"name":"Pare Ferrís - Menéndez Pidal"},{"id":1318,"name":"Molinell (par) - Alboraia"},{"id":1319,"name":"Corts Valencianes - Palau de Congressos"},{"id":1320,"name":"Camp de Túria (par) - Corts Valencianes"},{"id":1321,"name":"Camp de Túria (impar) - Corts Valencianes"},{"id":1326,"name":"Ninot - Foc"},{"id":1327,"name":"Francisco Morote Greus - Louis Braille"},{"id":1329,"name":"Palmaret - Montcada"},{"id":1330,"name":"Quartell - Burjassot"},{"id":1331,"name":"Florista - Carrasqueta"},{"id":1332,"name":"Florista - Faura"},{"id":1333,"name":"Bon Recés - Florista"},{"id":1348,"name":"Dr. Nicasi Benlloch - Emili Nadal"},{"id":1349,"name":"Sant Vicent Màrtir - Mossén Febrer"},{"id":135,"name":"Sants Just i Pastor - Humanista Furió"},{"id":1350,"name":"Sant Vicent Màrtir - Almudaina"},{"id":1352,"name":"la Plata - Alberola"},{"id":1353,"name":"la Plata - Ausiàs March"},{"id":1354,"name":"Bernat Descoll - Joaquín Benlloch"},{"id":1355,"name":"Oltà - Ausiàs March"},{"id":1356,"name":"la Plata - Fonteta Sant Lluís"},{"id":1357,"name":"la Plata - Actriu Pepita Serrador"},{"id":136,"name":"Sants Just i Pastor - Lleons"},{"id":1361,"name":"Tarongers - Ramon Llull"},{"id":1362,"name":"Tomàs Montañana - Albereda"},{"id":1363,"name":"Regne de València (impar) - Alcalde Reig"},{"id":1364,"name":"Regne de València (par) - Alcalde Reig"},{"id":1365,"name":"Tomàs Montañana - França"},{"id":1366,"name":"Alqueria Nova - Cortes d'Arenós"},{"id":1369,"name":"Tres Creus (central) - Pare Esteban Pernet"},{"id":137,"name":"Sants Just i Pastor - Dr. Manuel Candela"},{"id":1370,"name":"Pare Esteban Pernet - Misericòrdia"},{"id":1374,"name":"Punta al Mar (par) - Riu"},{"id":1375,"name":"Punta al Mar (par) - Canal"},{"id":1376,"name":"Camí del Canal (impar) - Guitarrista Tàrrega"},{"id":138,"name":"Sants Just i Pastor - República Argentina"},{"id":1380,"name":"Punta al Mar (impar) - Canal"},{"id":1381,"name":"Punta al Mar (impar) - Riu"},{"id":1382,"name":"Blasco Ibáñez (central) - Hospital Clínic"},{"id":1384,"name":"Serradora - Poliesportiu"},{"id":1385,"name":"Martí Grajales - Serradora"},{"id":1386,"name":"Serradora - Ambulatori"},{"id":1387,"name":"Sants Just i Pastor - Fusta"},{"id":139,"name":"Sants Just i Pastor - Lluís de Milà"},{"id":14,"name":"Cavite - Riu Tajo"},{"id":140,"name":"Sants Just i Pastor - Duc de Gaeta"},{"id":1409,"name":"Blasco Ibáñez - Manuela Estelles"},{"id":141,"name":"Sants Just i Pastor - Peris Brell"},{"id":1410,"name":"Guillermina Medrano (impar) - Borbotó"},{"id":1411,"name":"Guillermina Medrano (par) - Borbotó"},{"id":1413,"name":"Real de Madrid - Entrada Pinet"},{"id":1416,"name":"Inst. Obrer de Val. (impar) - Autopista Saler"},{"id":1417,"name":"Inst. Obrer de Val. (impar) - Amado Granell Mesado"},{"id":1418,"name":"Inst. Obrer de Val. (par) - Amado Granell Mesado"},{"id":1419,"name":"Inst. Obrer de Val. (par) - Autopista Saler"},{"id":1421,"name":"Petxina - Torres"},{"id":1422,"name":"Petxina - Pérez Galdos"},{"id":1423,"name":"Petxina - Terol"},{"id":1424,"name":"Petxina - Ferran el Catòlic"},{"id":1425,"name":"Petxina - Túria"},{"id":1427,"name":"Jacinto Benavente - Borriana"},{"id":1428,"name":"Jacinto Benavente - Peris i Valero"},{"id":1430,"name":"Albereda - Illes Canàries"},{"id":1431,"name":"Tirso de Molina - Pius XII"},{"id":1432,"name":"Tirso de Molina - Mestre Rodrigo"},{"id":1435,"name":"Tres Creus - Prínceps de Mònaco"},{"id":1436,"name":"Ausiàs March - Dr. Waksman"},{"id":1438,"name":"Dr. Tomàs Sala - Gaspar Aguilar"},{"id":144,"name":"Dr. Manuel Candela (par) - Rodríguez de Cepeda"},{"id":1440,"name":"Dr. Tomàs Sala - Sant Marcel.lí"},{"id":1441,"name":"Dr. Tomàs Sala (par) - Sant Vicent Màrtir"},{"id":1442,"name":"Dr. Tomàs Sala (impar) - Sant Vicent Màrtir"},{"id":1443,"name":"Dr. Tomàs Sala - Carters"},{"id":1444,"name":"Dr. Tomàs Sala - Jerónima Galés"},{"id":1448,"name":"Camp de Túria - Mestre Rodrigo"},{"id":145,"name":"Dr. Manuel Candela (par) - Blasco Ibáñez"},{"id":1461,"name":"França - Albereda"},{"id":1462,"name":"Albereda - Pont del Regne"},{"id":1463,"name":"Malilla (impar) - Illa Formentera"},{"id":1464,"name":"Malilla (impar) - Illa Cabrera"},{"id":1465,"name":"Malilla (impar) - Bernat Descoll"},{"id":1472,"name":"Pius IX - Salvador Perles"},{"id":1473,"name":"Pius IX - Cabanilles"},{"id":1474,"name":"Camí vell Picassent - Acc. Cementeri"},{"id":1475,"name":"Camí vell Picassent - Tanatori Municipal"},{"id":1484,"name":"Portugal - Canoner"},{"id":1485,"name":"Palmaret - Rosa dels Vents (davant)"},{"id":1489,"name":"Tarongers - Davant Acc.Pta.Prin.Universitats"},{"id":1490,"name":"Tarongers - Junt Entrada Universitats"},{"id":1492,"name":"Albalat dels Tarongers - Vinalopó"},{"id":1499,"name":"Sants Just i Pastor - Indústria"},{"id":150,"name":"Cardenal Benlloch (par) - Port"},{"id":1500,"name":"Sants Just i Pastor - Escultor Esteve Edo"},{"id":1501,"name":"Sants Just i Pastor - Serradora"},{"id":1503,"name":"Sants Just i Pastor - Music Ginés"},{"id":1515,"name":"Sants Just i Pastor - Jose Maria Haro"},{"id":1518,"name":"la Malva-rosa - Fuerteventura"},{"id":1520,"name":"Guillem de Castro - Sant Agustí"},{"id":1526,"name":"Dos de Mayo - Camí vell de Xirivella"},{"id":153,"name":"Cardenal Benlloch - Dr. Vicente Pallarés"},{"id":1532,"name":"Menorca - França"},{"id":1533,"name":"França - Higinio Noja"},{"id":1534,"name":"França-Vicente Beltrán"},{"id":1535,"name":"França-Pare Tomas Montañana"},{"id":1536,"name":"Albereda - Eduard Boscà"},{"id":1537,"name":"Albereda - Pont Àngel Custodi"},{"id":1538,"name":"França-Albereda"},{"id":1539,"name":"França-Pintor Maella"},{"id":154,"name":"Blasco Ibáñez - Rubén Darío"},{"id":1540,"name":"França-Trafalgar"},{"id":1541,"name":"Menorca - Balears"},{"id":1543,"name":"Xàtiva - Institut"},{"id":1546,"name":"Gran Canària - Mendizábal"},{"id":1547,"name":"Uruguai - Crta. Escrivà"},{"id":1548,"name":"Maximilià Thous - Constitució"},{"id":155,"name":"Blasco Ibáñez - Almela i Vives"},{"id":1550,"name":"Beat Juan Grande - Sant Joan de Déu"},{"id":1551,"name":"Tarongers - Pare Antón Martí"},{"id":1552,"name":"Marí Blas de Lezo - Felip Gauna"},{"id":1562,"name":"Palmaret - Rosa dels Vents"},{"id":1563,"name":"Sant Agustí - Sant Pau"},{"id":1566,"name":"Corts Valencianes (impar) - la Safor"},{"id":157,"name":"Blasco Ibáñez - Gascó Oliag"},{"id":1572,"name":"Sant Antoni - del Quint"},{"id":1574,"name":"Ferran el Catòlic - Petxina"},{"id":158,"name":"Blasco Ibáñez (impar) - Ciutat Universitària"},{"id":1584,"name":"Joaquím Ballester - Pare Ferrís"},{"id":1585,"name":"Castell de Pop - Jesús Natzaré"},{"id":1587,"name":"Reina - Armada Espanyola"},{"id":1589,"name":"Dr. J.J.Dòmine - Port"},{"id":1590,"name":"Joan Verdaguer - Port"},{"id":1591,"name":"Joan Verdaguer - Pare Porta"},{"id":1592,"name":"Joan Verdaguer - Issac Peral"},{"id":1593,"name":"Eivissa - Prof.Vicente Llorens"},{"id":1594,"name":"Illes Canàries - Noguera"},{"id":1595,"name":"Illes Canàries - Trafalgar"},{"id":1596,"name":"Illes Canàries - Vicente Beltrán"},{"id":1597,"name":"Illes Canàries - Lebon"},{"id":1598,"name":"Illes Canàries - Riu Escalona"},{"id":1599,"name":"Illes Canàries - Eduard Boscà"},{"id":16,"name":"Cavite - Vicent la Roda"},{"id":160,"name":"Blasco Ibáñez - Hospital Clínic"},{"id":1602,"name":"Serradora - Peanya"},{"id":1613,"name":"Marcos Sopena - Port"},{"id":1615,"name":"Port - Saragossa"},{"id":1616,"name":"Port - Eduard Boscà"},{"id":1617,"name":"Port - Riu Escalona"},{"id":1618,"name":"Port -Tomàs Montañana"},{"id":1619,"name":"Port - Cases Carbonell"},{"id":162,"name":"Blasco Ibáñez - Jaume Roig"},{"id":1621,"name":"Port - Noguera"},{"id":1622,"name":"Port - Eivissa"},{"id":1623,"name":"Port - Pare Porta"},{"id":1624,"name":"Port - Joan Josep Sister"},{"id":1627,"name":"Dr. Lluch - Armada Espanyola"},{"id":163,"name":"Blasco Ibáñez - General Elío"},{"id":1630,"name":"Menorca - Eivissa"},{"id":1631,"name":"Port - Illes Canàries"},{"id":1632,"name":"Marqués de Sotelo - Xátiva"},{"id":164,"name":"Blasco Ibáñez - Rectorat"},{"id":1646,"name":"la Plata - Músic Òscar Esplá"},{"id":165,"name":"Blasco Ibáñez (par) - Ciutat Universitària"},{"id":1651,"name":"Hernández Lázaro -Centre Comercial"},{"id":1652,"name":"Hernández Lázaro - Vall de la Ballestera"},{"id":1653,"name":"Mestre Rodrigo - General Avilés"},{"id":1654,"name":"Mestre Rodrigo - la Safor"},{"id":1655,"name":"Mestre Rodrigo - La Plana Baixa"},{"id":1657,"name":"Marina Baixa - Hospital Arnau de Vilanova"},{"id":1658,"name":"la Safor - Mestre Rodrigo"},{"id":1659,"name":"Mestre Rodrigo (Impar) - la Safor"},{"id":166,"name":"Blasco Ibáñez - Facultat de Geografia"},{"id":1660,"name":"Mestre Rodrigo (Impar) - General Avilés"},{"id":1661,"name":"Pío Baroja - Parc de capçalera"},{"id":1662,"name":"Vall de la Ballestera - Pío Baroja"},{"id":1663,"name":"Alcalde Reig - Pont del Regne"},{"id":1664,"name":"Alcalde Reig  - LLuís Oliag"},{"id":1665,"name":"Alcalde Reig (impar) - Pere Aleixandre"},{"id":167,"name":"Blasco Ibáñez - Facultat de Filologia"},{"id":1670,"name":"Reina - Remonta"},{"id":1671,"name":"Reina - Espadan"},{"id":1672,"name":"Reina - Pescadors"},{"id":1673,"name":"Reina - Vicent Gallart"},{"id":1675,"name":"Sueca - Puerto Rico"},{"id":1676,"name":"Sueca - G.V. Germanies"},{"id":1677,"name":"Cardenal Benlloch - Pobla Farnals"},{"id":1678,"name":"Cardenal Benlloch - Santos Justo y Pastor"},{"id":1679,"name":"Primat Reig - Conca Tramoyeres"},{"id":168,"name":"Blasco Ibáñez - Suècia"},{"id":1680,"name":"Primat Reig - Viver"},{"id":1681,"name":"Primat Reig - Motilla del Palancar"},{"id":1682,"name":"Primat Reig - Constitució"},{"id":1683,"name":"Dr. Peset Aleixandre - Montcada"},{"id":1684,"name":"Dr. Peset Aleixandre - Av. Burjassot"},{"id":1685,"name":"Campanar - Conchita Piquer"},{"id":1686,"name":"Pérez Galdós - Tres Forques"},{"id":1687,"name":"Giorgeta - Carcaixent"},{"id":1688,"name":"Peris i Valero - Escultor Josep Capuz"},{"id":169,"name":"Blasco Ibáñez - Bèlgica"},{"id":1690,"name":"Giorgeta - Albacete"},{"id":1691,"name":"Pérez Galdós - Martínez Aloy"},{"id":1692,"name":"Pérez Galdós - Heroi Romeu"},{"id":1693,"name":"Dr. Peset Aleixandre - En Guillem Ferrer"},{"id":1694,"name":"Primat Reig - Dr. Gómez Ferrer"},{"id":1695,"name":"Cardenal Benlloch - Dr. Ferran"},{"id":1696,"name":"Giorgeta - Mora de Rubielos"},{"id":17,"name":"Cavite - Font d'en Carròs"},{"id":170,"name":"Dr. Gómez Ferrer - Menéndez y Pelayo"},{"id":1700,"name":"Camp del Túria - Marina Baixa"},{"id":1701,"name":"Garrigues - Escolano"},{"id":1706,"name":"Rotonda Carretera Montanyars - Pinedo"},{"id":171,"name":"Cabanilles - Primat Reig"},{"id":1714,"name":"Fires(impar) - Cementeri"},{"id":1715,"name":"Fires(par) - Cementeri"},{"id":1716,"name":"Ferran el Catòlic - S. Ignacio de Loyola"},{"id":172,"name":"Cabanilles - Álvaro de Bazán"},{"id":1720,"name":"Corts Valencianes - Constitució"},{"id":1721,"name":"Corts Valencianes - Dr. Barraquer"},{"id":1723,"name":"Ribàs(par) - Dr. Ruiz Comes"},{"id":1724,"name":"Ribàs(impar) - Dr. Ruiz Comes"},{"id":173,"name":"Cabanilles - Vivers"},{"id":1733,"name":"Gaspar Aguilar - Hospital Peset"},{"id":1734,"name":"Carda - Moro Zeit"},{"id":174,"name":"Jaume Roig - Álvaro de Bazán"},{"id":1741,"name":"Pius XII - Melchor Hoyos Perez"},{"id":1742,"name":"Beat Juan Grande - Vicent la Roda"},{"id":1743,"name":"Albereda - Palau de la Música"},{"id":1744,"name":"Albereda (riu) - L'Hemisfèric"},{"id":1745,"name":"Albereda (riu) - Museu de les Ciències"},{"id":1746,"name":"Menorca (impar) - Centre Comercial"},{"id":1747,"name":"Serradora - Port"},{"id":1748,"name":"Serradora - Fco. Cubells"},{"id":1749,"name":"Lluís Peixò - Comte Melito"},{"id":175,"name":"Jaume Roig - Primat Reig"},{"id":1750,"name":"Fausto Elio (par) - Universitat Politècnica"},{"id":1751,"name":"Mendizábal - Gran Canària"},{"id":1752,"name":"Fausto Elio (impar) - Universitat Politècnica"},{"id":1753,"name":"Lluís Peixó - Tarongers"},{"id":1754,"name":"Marí Blas de Lezo - Cami Cabanyal"},{"id":1755,"name":"Marí Blas de Lezo(impar) -Estació Cabanyal"},{"id":1756,"name":"Serradora - Sants Just i Pastor"},{"id":1757,"name":"Serradora - Jeroni de Montsoriu"},{"id":1759,"name":"Menorca (par) - Centre Comercial"},{"id":1760,"name":"Albereda - Museu de les Ciències"},{"id":1761,"name":"Albereda - L'Hemisfèric"},{"id":1763,"name":"Jacinto Benavente - Pont Angel Custodi"},{"id":1764,"name":"Jacinto Benavente - Palau de la Música"},{"id":1765,"name":"Montolivet - Pere Aleixandre"},{"id":1766,"name":"Guillem de Castro - Hospital"},{"id":1767,"name":"Padilla - Músic Peydro"},{"id":1768,"name":"Marí Blas de Lezo(par) -Estació Cabanyal"},{"id":1769,"name":"La Murta (impar) - Cementeri"},{"id":177,"name":"Emili Baró - Reverend Rafael Tramoyeres"},{"id":1770,"name":"La Murta (impar) - Assagador la Torre"},{"id":1771,"name":"La Murta (par) - Assagador la Torre"},{"id":1772,"name":"La Murta (par) - Cementeri"},{"id":1773,"name":"Doctor Álvaro López - Illa de Hierro"},{"id":1774,"name":"Doctor Álvaro López - Vicent La Roda"},{"id":1775,"name":"Albereda (riu) - Illes Canàries"},{"id":1776,"name":"Albereda - Davant Palau de la Música"},{"id":178,"name":"Emili Baró - Manuel Castellanos"},{"id":1783,"name":"Uruguai (impar) - Jeroni Munyós"},{"id":1784,"name":"Carcaixent - Giorgeta"},{"id":1785,"name":"Uruguai (par) - Jeroni Munyós"},{"id":179,"name":"Emili Baró - Francesc Martínez"},{"id":18,"name":"Cavite - Mendizábal"},{"id":1801,"name":"Finlàndia - Aragó"},{"id":1802,"name":"Ernest Ferrer - Polo y Peirolón"},{"id":1804,"name":"Joaquín Costa - Comte d'Altea"},{"id":1805,"name":"Comte de Salvatierra - Ciril Amorós"},{"id":1806,"name":"Molinell (impar) - Alboraia"},{"id":1807,"name":"Argenter Suárez - Ministre Luis Mayans"},{"id":1808,"name":"Ruaya (par) - Visitació"},{"id":1809,"name":"Reus (impar) - Poeta Fdez. Heredia"},{"id":1810,"name":"Reus - Periodista Llorente"},{"id":1812,"name":"Joaquím Ballester - Pare Ferris"},{"id":1813,"name":"Reus - Alqueria de la Estrella"},{"id":1814,"name":"Reus (par) - Poeta Fdez. Heredia"},{"id":1815,"name":"Ruaya (impar) - Visitació"},{"id":1816,"name":"Argenter Suárez - Miraculosa"},{"id":1817,"name":"Font de la Figuera - Dr. Waksman"},{"id":1818,"name":"Sueca - Peris i Valero"},{"id":1819,"name":"Ausiàs March - Manuel Sanchis Guarner"},{"id":1820,"name":"Pedreguer - Juan Ramón Jiménez"},{"id":1821,"name":"Ausiàs March - Bernat Descoll"},{"id":1822,"name":"Ausiàs March - Na Rovella"},{"id":1824,"name":"Joan XXIII - Germans Machado"},{"id":1825,"name":"Joan XXIII - Federico Alcacer Aguilar"},{"id":1826,"name":"Joan XXIII (impar) - Félix del Río"},{"id":1827,"name":"General Avilés - Pius XII"},{"id":1828,"name":"General Avilés - Miguel Servet (impar)"},{"id":1829,"name":"General Avilés - Conchita Piquer"},{"id":1830,"name":"Joan XXIII - Pere Cabanes"},{"id":1831,"name":"Joan XXIII - Francisco Comes Martinez"},{"id":1832,"name":"Equador - Salvador Tuset"},{"id":1833,"name":"Equador - Verbena"},{"id":1834,"name":"Poeta Serrano Clavero - Equador"},{"id":1835,"name":"Federico Alcacer Aguilar - Poeta Serrano Clavero"},{"id":1836,"name":"Federico Alcacer Aguilar - Joan XXIII"},{"id":1837,"name":"Riu Nervión - Riu Segre"},{"id":1838,"name":"Duc de Mandas - Constitució"},{"id":1839,"name":"Duc de Mandas (par) - Arquitecto Rodríguez"},{"id":1840,"name":"Duc de Mandas - Motilla del Palancar"},{"id":1841,"name":"Valladolid - Vinaròs"},{"id":1842,"name":"Valladolid - Dolores Marqués"},{"id":1843,"name":"Duc de Mandas - Alfahuir"},{"id":1844,"name":"Duc de Mandas - Sant Vicent de Paül"},{"id":1845,"name":"Duc de Mandas (impar) - Arquitecto Rodríguez"},{"id":1846,"name":"Pere Cabanes - Camí Montcada"},{"id":1847,"name":"Castellonet - Joan XXIII"},{"id":1848,"name":"Castellonet - Alfara del Patriarca"},{"id":1849,"name":"Equador - General Llorens"},{"id":1850,"name":"Equador - Music Fayos"},{"id":1854,"name":"Peris i Valero - Duc de Calàbria"},{"id":1858,"name":"Castelló - Estació Nord"},{"id":1859,"name":"Carters - Pl. Santiago Suárez"},{"id":186,"name":"Primat Reig - Jaume Roig"},{"id":1860,"name":"Uruguai - Marques de Bellet"},{"id":1861,"name":"Constitució - Reig Genovés"},{"id":1862,"name":"Constitució - Coronel Montesinos"},{"id":1865,"name":"Pérez Galdós - Sant Josep de la Muntanya"},{"id":1866,"name":"Arxiduc Carles - Fontanars dels Aforins"},{"id":188,"name":"Primat Reig - Campus Universitari"},{"id":1883,"name":"Fra Juníper Serra -Torrent"},{"id":1885,"name":"Alcàsser - Ciutat de Mislata"},{"id":1886,"name":"Alcàsser - Poeta Alberto Lista"},{"id":1887,"name":"Blasco Ibañez - Palleter"},{"id":1888,"name":"Doctor J. J. Dòmine (via servici)- Port"},{"id":1895,"name":"Catalunya - Clariano"},{"id":1896,"name":"Tarongers - Facultat de Dret"},{"id":1897,"name":"Tarongers - Facultat d'Economia"},{"id":1898,"name":"Tarongers - Aparcament"},{"id":1900,"name":"Tarongers - Col.legi Major"},{"id":1901,"name":"Catalunya - Vicent Zaragozà"},{"id":1902,"name":"Catalunya - Guardia Civil"},{"id":1905,"name":"Tres Creus - Gaspar Aguilar"},{"id":1918,"name":"Tarongers - Fausto Elio"},{"id":1919,"name":"Parc Natzaret - Pont de les Drassanes"},{"id":192,"name":"Primat Reig - Camí Vera"},{"id":1922,"name":"Sant Antoni - Enric Valor"},{"id":1928,"name":"Gaspar Aguilar - Montesa"},{"id":1929,"name":"Gaspar Aguilar (par) - Dr. Tomas Sala"},{"id":1930,"name":"Gaspar Aguilar (impar) - Dr.Tomas Sala"},{"id":1931,"name":"Gaspar Aguilar - Músic Penella"},{"id":1932,"name":"Gaspar Aguilar - Costa i Borràs"},{"id":1936,"name":"Campos Crespo - Arquitecte Segura de Lago"},{"id":1937,"name":"Arquitecte Segura de Lago - Dr. Rafael Bartual"},{"id":1938,"name":"Tres Creus - Bolívia"},{"id":1939,"name":"Armada Espanyola - Francesc Cubells"},{"id":194,"name":"Primat Reig - Emili Baró"},{"id":1940,"name":"Músic Cuesta - Pare Presentat"},{"id":1941,"name":"Pérez Pujol - Correus"},{"id":1943,"name":"Bulevard Sud- Pont"},{"id":1944,"name":"Bulevard Sud (par) - Malilla"},{"id":1946,"name":"Bulevard Sud (par) - Hospital la Fe"},{"id":1947,"name":"Bulevard Sud (impar) - Juan Ramón Jiménez"},{"id":1950,"name":"Pere II El Cerimonios - Luis Merelo y Mas"},{"id":1951,"name":"Pere II El Cerimonios - Vicente Beltrán Grimalt"},{"id":1952,"name":"Pintor Maella - Vicent Vidal (Cronista)"},{"id":1953,"name":"Pintor Maella (par) - França"},{"id":1954,"name":"Pintor Maella - Luis Bolinches Compañ"},{"id":1955,"name":"Pintor Maella - Menorca"},{"id":1956,"name":"Pintor Maella (impar) - França"},{"id":1957,"name":"Pintor Maella - Balears"},{"id":1958,"name":"Pintor Maella - Illes Canàries"},{"id":1959,"name":"Blanqueria - Pare d' Òrfens"},{"id":1961,"name":"Alfahuir - Germans Machado"},{"id":1962,"name":"Mestre Rodrigo - Canal de Navarrés"},{"id":1963,"name":"Camí del Canal -Club Náutico"},{"id":1964,"name":"Bulevard Sud (impar) - Hospital la Fe"},{"id":1965,"name":"Bulevard Sud (impar) - Malilla"},{"id":1968,"name":"Ramón i Cajal - Plaça Espanya"},{"id":1969,"name":"San Vicent Màrtir - Mestre Sosa"},{"id":197,"name":"Primat Reig - Sant Vicent de Paül"},{"id":198,"name":"Pare Viñas - Reig Genovés"},{"id":1980,"name":"Major de Natzaret - Castell de Pop"},{"id":1981,"name":"Ares d'Alpont - Castell de Pop"},{"id":1988,"name":"Alfahuir - Cercle de Belles Arts"},{"id":1989,"name":"Alfahuir - Actor Ismael Merlo"},{"id":199,"name":"Pare Viñas - Duc de Mandas"},{"id":1990,"name":"Alfahuir - Dr. José Chabas Bordehore"},{"id":1991,"name":"Alfahuir - Arquitecte Tolsà"},{"id":1993,"name":"Ausiàs March - Oltà"},{"id":1994,"name":"Bulevard Sud - Ausiàs March"},{"id":1999,"name":"Tres Forques - Casa Misericòrdia"},{"id":20,"name":"la Malva-rosa - Mendizábal"},{"id":200,"name":"Pare Viñas - Daroca"},{"id":2004,"name":"Cid (via servici) - Alejandro Volta"},{"id":2005,"name":"Marconi - Barri de la Llum"},{"id":2006,"name":"Pare Esteban Pernet (impar) - Miquel Adlert"},{"id":2007,"name":"Pare Esteban Pernet - Casa Misericòrdia"},{"id":2008,"name":"Pare Esteban Pernet (par) - Miquel Adlert"},{"id":2009,"name":"Tres Creus - Music Ayllón"},{"id":2014,"name":"Poeta Querol - Barques"},{"id":202,"name":"Sant Joan Bosco - Daroca"},{"id":2027,"name":"Port - Trafalgar"},{"id":2030,"name":"Orxata - Ausiàs March"},{"id":2031,"name":"Giorgeta (par) - Roís de Corella"},{"id":2032,"name":"Comte de Trénor - Pont de Fusta"},{"id":2034,"name":"Cronista Rivelles - Pl. Sta. Mónica"},{"id":2041,"name":"Professor López Piñero (par) - Institut Obrer de València"},{"id":2042,"name":"Professor López Piñero (par)  - Ciutat de la Justícia"},{"id":2043,"name":"Eduardo Primo Yúfera - Front Àgora"},{"id":2044,"name":"Eduardo Primo Yúfera - Front Oceanogràfic"},{"id":2045,"name":"Eduardo Primo Yúfera - Front Centre Investigació"},{"id":2046,"name":"Barraques del Figuero (par) - Llauradors"},{"id":2047,"name":"Barraques del Figuero - Ignacio Zuloaga"},{"id":2048,"name":"Barraques del Figuero - Cocoters"},{"id":2049,"name":"Barraques del Figuero (impar) - Llauradors"},{"id":2050,"name":"Eduardo Primo Yúfera - Centre d'Investigació"},{"id":2051,"name":"Eduardo Primo Yúfera - Oceanogràfic"},{"id":2052,"name":"Eduardo Primo Yúfera - Àgora"},{"id":2053,"name":"Professor López Piñero - Museu de les Ciències"},{"id":2054,"name":"Professor López Piñero (impar) - Institut Obrer de València"},{"id":2059,"name":"Eivissa - Port"},{"id":206,"name":"Primat Reig - Bilbao"},{"id":2060,"name":"Eivissa (par) - Illes Canàries"},{"id":2062,"name":"Eugènia Viñes - Platja de les Arenes"},{"id":2063,"name":"Cases de Bàrcena - Rotonda"},{"id":2064,"name":"Terrateig - Jorge Comín"},{"id":2066,"name":"Vall de la Ballestera (impar) - Hernández Lázaro"},{"id":2067,"name":"Vall de la Ballestera - Eduardo Soler i Pérez"},{"id":2069,"name":"Terrateig - Poeta Rafael Alberti"},{"id":207,"name":"Primat Reig - Almassora"},{"id":2070,"name":"Nou d'Octubre (par) - Democràcia"},{"id":2071,"name":"Nou d'Octubre - Conselleries (I)"},{"id":2072,"name":"Nou d'Octubre - Conselleries (II)"},{"id":2077,"name":"Germanies - Alacant"},{"id":2078,"name":"Filipines - Literat Azorín"},{"id":2080,"name":"Germanies - Cuba"},{"id":2084,"name":"Vinalesa"},{"id":2085,"name":"Cecili Pla - Germans Machado"},{"id":2086,"name":"Racó d'Ademús - Conselleries"},{"id":2093,"name":"Manuel de Falla - Hernández Lázaro"},{"id":2094,"name":"Molinell (par) - Pintor Genaro Lahuerta"},{"id":2095,"name":"Molinell (impar) - Pintor Genaro Lahuerta"},{"id":2096,"name":"Pío Baroja - Manuel de Falla"},{"id":2097,"name":"Vall de la Ballestera (impar) - Mestre Rodrigo"},{"id":2098,"name":"Vall de la Ballestera - Luis Buñuel"},{"id":2099,"name":"Nou d'Octubre - Av. del Cid"},{"id":2100,"name":"Tres Creus (par) - Campos Crespo"},{"id":2105,"name":"Moncada - Alfara"},{"id":2111,"name":"Mare Nostrum - Illa de Tabarca"},{"id":2112,"name":"Mare Nostrum - Mar Tirreno"},{"id":2113,"name":"Blasco Ibáñez - Mar Tirreno"},{"id":2114,"name":"Blasco Ibáñez"},{"id":2122,"name":"Punta al Mar - Algemesí"},{"id":2127,"name":"Filipines - Gibraltar"},{"id":2128,"name":"Filipines - Puerto Rico"},{"id":215,"name":"Alboraia - Primat Reig"},{"id":2154,"name":"Filipines - Manuel Sanchis Guarner"},{"id":2157,"name":"Ausiàs March - Pianista Martínez Carrasco"},{"id":2158,"name":"Bulevard Sud - Ing. Joaquín Benlloch"},{"id":2159,"name":"Joaquin Benlloch - Pl. Pintor Andreu"},{"id":216,"name":"Primat Reig - Calderón de la Barca"},{"id":2160,"name":"Burjassot - Marxalenes"},{"id":2161,"name":"Rafael Tenes Escrich - Mercat"},{"id":2163,"name":"Carrera del Riu (par) - Coll Vert"},{"id":2164,"name":"Carrera del Riu (par) - Camping Valencia"},{"id":2165,"name":"Pinars (par) - El Saler"},{"id":2166,"name":"Gola de Puchol (I)"},{"id":2167,"name":"Gola de Puchol (II)"},{"id":2168,"name":"Embarcador de l'Albufera (I)"},{"id":2169,"name":"Pinars - Carretera del Palmar"},{"id":2170,"name":"Carretera del Palmar (par) - Cementeri"},{"id":2171,"name":"Vicent Baldoví - Novelda"},{"id":2172,"name":"Vicent Baldoví - el Palmar"},{"id":2173,"name":"Vicent Baldoví - Pintor Martí Girbés"},{"id":2174,"name":"Carretera del Palmar (impar) - Cementeri"},{"id":2175,"name":"Carretera del Palmar - Pinars"},{"id":2176,"name":"Gavines (par) - Camping"},{"id":2177,"name":"Gavines - Sotavent"},{"id":2178,"name":"Gavines - Entrada Trenca Perols"},{"id":2179,"name":"Gavines - Entrada Filero"},{"id":2180,"name":"Gavines (par) - Platja"},{"id":2181,"name":"Gavines (par) - Sirena"},{"id":2182,"name":"Gavines - Entrada Paridera"},{"id":2183,"name":"Gavines - Entrada Ventura"},{"id":2184,"name":"Gavines (par) - Les Escales"},{"id":2185,"name":"Gavines - Entrada a la Baixada del Pantà"},{"id":2187,"name":"Gavines - Bitàcora"},{"id":2188,"name":"Gavines (impar) - Les Escales"},{"id":2189,"name":"Gavines - Front Entrada Ventura"},{"id":219,"name":"Aragó - Passeig Albereda"},{"id":2190,"name":"Gavines - Dofins"},{"id":2191,"name":"Gavines (impar) - Sirena"},{"id":2192,"name":"Gavines (impar) - Platja"},{"id":2193,"name":"Gavines - Les dunes"},{"id":2194,"name":"Gavines - Botavara"},{"id":2195,"name":"Gavines (impar) - Camping"},{"id":2196,"name":"Embarcador de l'Albufera (II)"},{"id":2197,"name":"Gola de Puchol (III)"},{"id":2198,"name":"Gola de Puchol (IV)"},{"id":2199,"name":"Platja del Saler"},{"id":2200,"name":"Pinars (impar) - El Saler"},{"id":2201,"name":"Carrera del Riu (impar) - Camping Valencia"},{"id":2202,"name":"Carrera del Riu (impar) - Coll Vert"},{"id":2203,"name":"Carrera del Riu - Montanyars"},{"id":2205,"name":"Albufera - Pl. de la Sequiota"},{"id":2206,"name":"Pl. Amèrica - Navarro Reverter"},{"id":2207,"name":"Carrera del Riu (par) - Rotonda Autovia"},{"id":2208,"name":"Carrera del Riu (impar) - Rotonda Autovia"},{"id":2210,"name":"Sant Vicent Màrtir - Ànimes"},{"id":2213,"name":"Aragó (impar) - Blasco Ibáñez"},{"id":2214,"name":"Mercat Central - Llotja"},{"id":2218,"name":"Centelles - Filipines"},{"id":2220,"name":"Pl. de l'Ajuntament - Mercat Central - Llotja"},{"id":2223,"name":"Tetuan"},{"id":2224,"name":"Ignacio de Zuloaga - Castell de Pop"},{"id":2225,"name":"Camí Nou de Paterna - Aldaia"},{"id":2226,"name":"Campament - Canonge Fenollera"},{"id":223,"name":"General Elío - Blasco Ibáñez"},{"id":2230,"name":"Camp de Túria - Palau de Congressos"},{"id":2231,"name":"Alboraia - Pintor Vilar"},{"id":2232,"name":"Alboraia - Jaca"},{"id":2233,"name":"Almassora - Argenter Suàrez"},{"id":2234,"name":"Almassora - Pintor Vilar"},{"id":2235,"name":"Actor Antonio Ferrandis (par) - Centre Comercial"},{"id":2236,"name":"Actor Antonio Ferrandis (par) - Amado Granell Mesado"},{"id":2237,"name":"Actor Antonio Ferrandis (par) - En Corts"},{"id":2238,"name":"Actor Antonio Ferrandis (par) - Font de St. Lluís"},{"id":2239,"name":"Actor Antonio Ferrandis (impar) - Font de St. Lluís"},{"id":224,"name":"General Elío - Vivers"},{"id":2240,"name":"Actor Antonio Ferrandis (impar) - En Corts"},{"id":2241,"name":"Actor Antonio Ferrandis (impar) - Amado Granell Mesado"},{"id":2242,"name":"Actor Antonio Ferrandis (impar) - Centre Comercial"},{"id":2243,"name":"Tres Creus - Campos Crespo"},{"id":2244,"name":"Tres Creus - Arxiduc Carles"},{"id":2245,"name":"Tres Creus - Marià de Càvia"},{"id":2246,"name":"Mare Nostrum - Alboran"},{"id":2247,"name":"Mare Nostrum - la Patacona"},{"id":2248,"name":"Blasco Ibáñez - la Patacona"},{"id":2249,"name":"Casa Misericòrdia (impar) - Escultor Salzillo"},{"id":225,"name":"Cardenal Benlloch - Ciutat de Mula"},{"id":2250,"name":"Porta de la Mar (par) - Navarro Reverter"},{"id":2251,"name":"Porta de la Mar (impar) - Navarro Reverter"},{"id":2252,"name":"Porta de la Mar - Carrer del Justícia"},{"id":2256,"name":"Porta de la Mar (par) - Palau de Justícia"},{"id":226,"name":"Cardenal Benlloch - Ernest Ferrer"},{"id":2262,"name":"Palmaret (par) - Montcada"},{"id":2263,"name":"Marcos Sopena - Eugènia Viñes"},{"id":2266,"name":"Fra Juníper Serra (par) - Torrent"},{"id":2267,"name":"Fra Juníper Serra - Tres Forques"},{"id":227,"name":"Ernest Ferrer - Polo y Peyrolón"},{"id":2270,"name":"Tarongers - Progrés"},{"id":2271,"name":"Passeig Marítim - Pavia"},{"id":2273,"name":"Oltà - Joaquín Benlloch"},{"id":2288,"name":"Av. de l'Oest - Beata"},{"id":2289,"name":"Av. de l'Oest - Roger de Flor"},{"id":229,"name":"Cardenal Benlloch (impar) - Port"},{"id":2290,"name":"Av. de l'Oest - Hospital"},{"id":2291,"name":"Amado Granell Mesado (par) - Lluís Oliag"},{"id":2292,"name":"Amado Granell Mesado (par) - la Plata"},{"id":2293,"name":"Amado Granell Mesado (par) - Arabista Ambrosio Huici"},{"id":2294,"name":"Amado Granell Mesado (par) - Antonio Sacramento"},{"id":2295,"name":"Amado Granell Mesado (par) - Antonio Ferrandis"},{"id":2296,"name":"Amado Granell Mesado (impar) - Antonio Ferrandis"},{"id":2297,"name":"Amado Granell Mesado (impar) - Antonio Sacramento"},{"id":2298,"name":"Amado Granell Mesado (impar) - Arabista Ambrosio Huici"},{"id":2299,"name":"Amado Granell Mesado (impar) - la Plata"},{"id":230,"name":"Eduard Boscà - Passeig de l'Albereda"},{"id":2300,"name":"Amado Granell Mesado (impar) - Lluís Oliag"},{"id":2301,"name":"Félix del Río - Camí de Montcada"},{"id":2303,"name":"Andreu Alfaro - Louis Braille"},{"id":2304,"name":"Democràcia - Baladre"},{"id":2305,"name":"Democràcia - Velázquez"},{"id":2306,"name":"Democràcia - Conselleries"},{"id":2307,"name":"General Avilés (illeta) - Pius XII"},{"id":2309,"name":"Estació del Nord - Bailén"},{"id":231,"name":"Eduard Boscà - Balears"},{"id":2318,"name":"Quevedo - Av. de l'Oest"},{"id":2320,"name":"Primer de Maig - Gaspar Aguilar"},{"id":2323,"name":"Mediterrània - Font Podrida"},{"id":2324,"name":"França - Camí Fondo del Grao"},{"id":2326,"name":"Columbretes - Eugènia Viñes"},{"id":2327,"name":"Séquia de la Cadena - Forn del Cabanyal"},{"id":2328,"name":"Eugènia Viñes - Historiador Coloma"},{"id":238,"name":"Dr. Peset Aleixandre - Joan XXIII"},{"id":24,"name":"la Malva-rosa - Sant Rafael"},{"id":242,"name":"Dr. Peset Aleixandre - Guardacostes"},{"id":243,"name":"Dr. Peset Aleixandre - Camí de Montcada"},{"id":244,"name":"Dr. Peset Aleixandre - Constitució"},{"id":246,"name":"Constitució - Duc de Mandas"},{"id":247,"name":"Constitució - Sant Joan de la Penya"},{"id":248,"name":"Constitució - Sant Miquel dels Reis"},{"id":249,"name":"Constitució (par) - Campaneta"},{"id":25,"name":"la Malva-rosa - Sant Joan de Deu"},{"id":250,"name":"Constitució (par) - Tavernes Blanques"},{"id":257,"name":"Constitució (impar) - Tavernes Blanques"},{"id":258,"name":"Constitució (impar) - Campaneta"},{"id":259,"name":"Constitució - Camí Àngel"},{"id":26,"name":"la Malva-rosa - Riu Tajo"},{"id":268,"name":"Joan XXIII (par) - Félix del Río"},{"id":272,"name":"Sant Doménec Savio - Mestre Marçal"},{"id":273,"name":"Sant Doménec Savio - Constitució"},{"id":279,"name":"Camí de Montcada - Dr. Peset Aleixandre"},{"id":280,"name":"Camí de Montcada (par) - Cambrils"},{"id":281,"name":"Camí de Montcada (par) - Alemany"},{"id":282,"name":"Camí de Montcada - Entrada Camí Carpesa"},{"id":283,"name":"Camí de Montcada - Poble Nou"},{"id":284,"name":"Camí de Montcada - Casa d'Àngel"},{"id":285,"name":"Cami de Montcada - Alqueria Ballester"},{"id":286,"name":"Camí de Montcada (par) - Matador"},{"id":290,"name":"Palmaret - Reverend J. Valero"},{"id":291,"name":"Camí de Montcada (par) - Alqueria Senent"},{"id":292,"name":"Benifaraig a Montcada - Casa Silvestre"},{"id":296,"name":"Benifaraig a Montcada - Boquera"},{"id":297,"name":"Camí de Montcada (impar) - Alqueria Senent"},{"id":299,"name":"Camí de Montcada (impar) - Matador"},{"id":300,"name":"Camí de Montcada - Alqueria Paella"},{"id":301,"name":"Camí de Montcada - Ctra. Daniel"},{"id":302,"name":"Camí de Montcada - Camí a Poble Nou"},{"id":303,"name":"Camí de Montcada - Ctra. Carpesa"},{"id":304,"name":"Camí de Montcada (impar) - Alemany"},{"id":305,"name":"Camí de Montcada (impar) - Cambrils"},{"id":306,"name":"Camí de Montcada - Félix del Río"},{"id":307,"name":"Burjassot - Mondúver"},{"id":308,"name":"Burjassot - Pintor Matarana"},{"id":309,"name":"Burjassot - Salvador Tuset"},{"id":310,"name":"Louis Braille - Betxí"},{"id":311,"name":"Sant Josep Artesà - Luis Martí Alegre"},{"id":314,"name":"Louis Braille - Burjassot"},{"id":318,"name":"Dr. Nicasi Benlloch - General Avilés"},{"id":319,"name":"Campanar - Dr. Nicasi Benlloch"},{"id":321,"name":"Sagunt - Sant Guillem"},{"id":322,"name":"Sagunt - Fra Pere Vives"},{"id":323,"name":"Sagunt - Pare Urbà"},{"id":324,"name":"Sagunt - Don Bosco"},{"id":325,"name":"Constitució - Dr. Peset Aleixandre"},{"id":326,"name":"Constitució - Xest"},{"id":327,"name":"Constitució - Sarrión"},{"id":328,"name":"Constitució - Màlaga"},{"id":329,"name":"Constitució - Pla de la Saïdia"},{"id":330,"name":"Burjassot - Màlaga"},{"id":331,"name":"Burjassot - Reus"},{"id":333,"name":"Burjassot - Dr. Peset Aleixandre"},{"id":334,"name":"Camí de Montcada - Economista Gay"},{"id":337,"name":"Dr. Moliner - Arts Gràfiques"},{"id":338,"name":"Sant Pius V - Alboraia"},{"id":339,"name":"la Plata - Sapadors"},{"id":341,"name":"Cronista Rivelles - Santa Amàlia"},{"id":342,"name":"Guadalaviar - Sagunt"},{"id":343,"name":"Pla de la Saïdia - Constitució"},{"id":344,"name":"Pla de la Saïdia - Burjassot"},{"id":345,"name":"Menéndez Pidal (par) - Pare Ferrís"},{"id":346,"name":"Menéndez Pidal - Estació d'autobusos"},{"id":347,"name":"Menéndez Pidal - Passarel.la"},{"id":348,"name":"Menéndez Pidal - Estació d'autobusos (riu)"},{"id":349,"name":"Menéndez Pidal (impar) - Pare Ferrís"},{"id":350,"name":"Pla de la Saïdia - Pont Sant Josep"},{"id":351,"name":"Pla de la Saïdia (riu) - Constitució"},{"id":352,"name":"Guadalaviar - Pont dels Serrans"},{"id":353,"name":"Dr. Nicasi Benlloch - Alcubles"},{"id":354,"name":"Pare Ferrís - Joaquím Ballester"},{"id":358,"name":"Joaquím Ballester (par) - Ricardo Micó"},{"id":359,"name":"Joaquím Ballester - Campanar"},{"id":361,"name":"Joaquím Ballester (impar) - Ricardo Micó"},{"id":364,"name":"Campanar - Ricardo Micó"},{"id":367,"name":"Campanar - Joan Pau II"},{"id":368,"name":"Campanar - Tirso de Molina"},{"id":370,"name":"Campanar - Pius XII"},{"id":371,"name":"Pius XII - Menéndez Pidal"},{"id":372,"name":"Pius XII - Campanar"},{"id":373,"name":"Pius XII (par) - Monestir de Poblet"},{"id":375,"name":"Corts Valencianes - Davant Esc. Prof. Sant Josep"},{"id":376,"name":"Corts Valencianes (par) - la Safor"},{"id":381,"name":"Mossén Miguel Tarin (impar) - Carretera de Paterna"},{"id":382,"name":"Mossén Miguel Tarin (impar) - Miquel Agraït"},{"id":383,"name":"Dr. Soriano Benlloch - Rafael Tenes Escrich"},{"id":384,"name":"Lluís Cano"},{"id":385,"name":"Campament - Felipe Valls"},{"id":386,"name":"Campament (par) - Joaquín Marín"},{"id":387,"name":"Polvorí - Sinarques"},{"id":388,"name":"Fires - Senda del Polvorí"},{"id":389,"name":"Alginet - Algemesí"},{"id":390,"name":"Almassora - Terramelar"},{"id":391,"name":"Alginet - Alcossebre"},{"id":392,"name":"Fires - Fira de Mostres"},{"id":393,"name":"Polvorí - Velòdrom Lluis Puig"},{"id":394,"name":"Polvorí - Campament"},{"id":395,"name":"Campament (impar) - Joaquín Marín"},{"id":396,"name":"Pintor Garnelo - Campament"},{"id":397,"name":"Felipe Valls - Lluís Cano"},{"id":399,"name":"Mossén Miguel Tarin (par) - Miquel Agraït"},{"id":400,"name":"Mossén Miguel Tarin (par) - Carretera de Paterna"},{"id":403,"name":"Corts Valencianes - l'Alt Maestrat"},{"id":405,"name":"Corts Valencianes - Esc. Prof. de Sant Josep"},{"id":407,"name":"Pius XII - Bisbe Soler"},{"id":409,"name":"Pius XII - Tirso de Molina"},{"id":415,"name":"Vall de la Ballestera (par) - Mestre Rodrigo"},{"id":419,"name":"Manuel de Falla - Mestre Rodrigo"},{"id":420,"name":"Manuel de Falla - Grup Parpalló"},{"id":422,"name":"Mestre Rodrigo - Manuel de Falla"},{"id":425,"name":"Pérez Galdós - Democràcia"},{"id":426,"name":"Pérez Galdós - Torres Torres"},{"id":427,"name":"Pérez Galdós - Olimpia Arozena Torres"},{"id":428,"name":"Llorca - Pérez Galdós"},{"id":432,"name":"Pérez Galdós - Lladró i Mallí"},{"id":434,"name":"Giorgeta - Ctra. D'Escrivà"},{"id":436,"name":"Giorgeta - Roís de Corella"},{"id":439,"name":"Pérez Galdós - Conca"},{"id":44,"name":"Pintor Ferrandis - Progrés"},{"id":441,"name":"Pérez Galdós - Calixt III"},{"id":442,"name":"Pérez Galdós - Mestre Guerrero"},{"id":443,"name":"Pérez Galdós - Dr. Zamenhof"},{"id":445,"name":"Joan XXIII - Periodista Gil Sumbiela"},{"id":45,"name":"Pintor Ferrandis - Josep Benlliure"},{"id":450,"name":"Sant Antoni - La Senyera"},{"id":451,"name":"Sant Antoni - Mare de Déu dels Desamparats"},{"id":452,"name":"Sant Antoni - Túria"},{"id":454,"name":"Sant Antoni - José Pomer"},{"id":455,"name":"Sant Antoni - Marcos Porta"},{"id":456,"name":"Sant Antoni - Major"},{"id":46,"name":"Pintor Ferrandis - Àngels"},{"id":467,"name":"Blasco Ibáñez - Gregori Gea"},{"id":47,"name":"Església dels Àngels - Pintor Ferrandis"},{"id":472,"name":"Petxina - Racó d'Ademús"},{"id":473,"name":"Brasil - Velàzquez"},{"id":474,"name":"Brasil - Francisco Moreno Usedo"},{"id":475,"name":"Brasil - Artur Piera"},{"id":481,"name":"Linares - Pérez Galdós"},{"id":482,"name":"Cid - Germans Rivas"},{"id":483,"name":"Cid - Burgos"},{"id":484,"name":"Cid - Passatge Vidal"},{"id":485,"name":"Cid - Nou d'Octubre"},{"id":486,"name":"Cid - Particular"},{"id":487,"name":"Cid - Pere Maria Orts"},{"id":488,"name":"Cid - Marcelino Oreja"},{"id":493,"name":"Joan Baptista Comes - Antonio Machado"},{"id":495,"name":"Cid - Marconi"},{"id":496,"name":"Cid - Hospital"},{"id":498,"name":"Tres Creus (carril bus) - Rei Saud"},{"id":50,"name":"Reina - Columbretes"},{"id":500,"name":"Escultor Salzillo - Casa de la Misericòrdia"},{"id":501,"name":"Colònia Esp. de Mèxic - Casa de la Misericòrdia"},{"id":504,"name":"Tres Creus - Jurats"},{"id":506,"name":"Cid - Josep Maestre"},{"id":507,"name":"Cid - Santa Cruz de Tenerife"},{"id":508,"name":"Cid - Ènguera"},{"id":509,"name":"Arxiduc Carles - Xiva"},{"id":510,"name":"Arxiduc Carles - Énguera"},{"id":511,"name":"Tres Forques (par) - Arxiduc Carles"},{"id":512,"name":"Tres Forques - Santa Cruz de Tenerife"},{"id":513,"name":"Tres Forques - Josep Maestre"},{"id":514,"name":"Tres Creus (carril bus) - Llombai"},{"id":515,"name":"Tres Creus (carril bus) - Músic Ayllón"},{"id":524,"name":"José Andreu Alabarta - Mariano de Cavia"},{"id":525,"name":"José Andreu Alabarta - Professor Àngel Lacalle"},{"id":529,"name":"Tres Forques - Emili Lluch"},{"id":530,"name":"Tres Forques - Mare de Déu de la Cabeça"},{"id":531,"name":"Tres Forques (impar) - Arxiduc Carles"},{"id":532,"name":"Tres Forques - Churat i Saurí"},{"id":533,"name":"Tres Forques - Pérez Galdós"},{"id":534,"name":"Tres Forques - Xiva"},{"id":535,"name":"Tres Forques - Mestre Bellver"},{"id":538,"name":"Arxiduc Carles (par) - Fra Juníper Serra"},{"id":539,"name":"Arxiduc Carles - Puebla Valverde"},{"id":54,"name":"Mercat el Cabanyal - Martí Grajales"},{"id":540,"name":"Camí nou de Picanya - Tres Creus"},{"id":543,"name":"Arxiduc Carles - Músic Gomis"},{"id":544,"name":"Arxiduc Carles - Fra Juníper Serra"},{"id":545,"name":"Arquitecte Segura de Lago - Prof. Àngel Lacalle"},{"id":546,"name":"Jesús - Callosa d'en Sarrià"},{"id":548,"name":"Jesús (Plaça) - Beat Nicolau Factor"},{"id":549,"name":"Beat Nicolau Factor - Lladró i Mallí"},{"id":550,"name":"Humanista Mariner - Beat Nicolau Factor"},{"id":551,"name":"Fontanars dels Aforins - Humanista Mariner"},{"id":552,"name":"Pius XI - Manuel Simó"},{"id":554,"name":"Conca - Mossén Fenollar"},{"id":555,"name":"Conca - Pérez Galdós"},{"id":557,"name":"Gaspar Aguilar - Jesús"},{"id":559,"name":"Gaspar Aguilar - Fontanars dels Alforins"},{"id":563,"name":"Gaspar Aguilar -Crematorio"},{"id":564,"name":"Sant Doménec de Guzman - Cementeri"},{"id":571,"name":"Gaspar Aguilar - Calvo Acacio"},{"id":575,"name":"Sant Vicent Màrtir - Dolores Alcaide"},{"id":576,"name":"Sant Vicent Màrtir - Joaquín Navarro"},{"id":577,"name":"Sant Vicent Màrtir - Primer de Maig"},{"id":578,"name":"Sant Vicent Màrtir - Enginyer Josep Sirera"},{"id":579,"name":"Sant Vicent Màrtir (par) - Arquebisbe Olaechea"},{"id":58,"name":"Manuel Soto Enginyer - Estació"},{"id":580,"name":"José Soto Micó - Alcalà de Xivert"},{"id":581,"name":"Real de Madrid - Carretera d'Alba"},{"id":582,"name":"Real de Madrid - Algar del Palància"},{"id":583,"name":"Real de Madrid (par) - Eduardo Dato"},{"id":585,"name":"Guadalquivir - Forn d'Alcedo"},{"id":586,"name":"Manuel Iranzo - Real de Madrid"},{"id":588,"name":"Real de Madrid - Hellín"},{"id":589,"name":"Real de Madrid - Concepción Arenal"},{"id":59,"name":"Manuel Soto Enginyer - Comandància Marina"},{"id":590,"name":"José Soto Micó - Síndic Mojolí"},{"id":591,"name":"Sant Vicent Màrtir (impar) - Arquebisbe Olaechea"},{"id":592,"name":"Sant Vicent Màrtir - Rambleta"},{"id":593,"name":"Sant Vicent Màrtir - Altamira"},{"id":594,"name":"Sant Vicent Màrtir - Fernández de Mesa"},{"id":595,"name":"Sant Vicent Màrtir - Millars"},{"id":596,"name":"Peris i Valero - Ausiàs March"},{"id":598,"name":"Peris i Valero - Sapadors"},{"id":599,"name":"Peris i Valero - Bisbe Jaume Pérez"},{"id":60,"name":"Manuel Soto Enginyer - Pont de les Drassanes"},{"id":600,"name":"Peris i Valero - Pere Aleixandre"},{"id":602,"name":"Mestre Racional - Regne de València"},{"id":603,"name":"Maties Perelló - Lluis de Santangel"},{"id":604,"name":"Maties Perelló - Mestre Aguilar"},{"id":605,"name":"dels Centelles - Sueca"},{"id":606,"name":"Filipines - Manuel Sanchis Guarner"},{"id":609,"name":"Malilla - Pianista Empar Iturbi"},{"id":61,"name":"Major de Natzaret - Vilanova i Piera"},{"id":610,"name":"Malilla - Oltà"},{"id":611,"name":"Malilla (par) - Illa Cabrera"},{"id":612,"name":"Malilla (par) - Illa Formentera"},{"id":62,"name":"Major de Natzaret - Moraira"},{"id":620,"name":"Joaquín Benlloch - Illa Cabrera"},{"id":621,"name":"Joaquín Benlloch - Oltà"},{"id":622,"name":"Joaquín Benlloch - Pianista Empar Iturbi"},{"id":623,"name":"Pianista Empar Iturbi - Ausiàs March"},{"id":625,"name":"Fonteta Sant Lluís - Lleó XIII"},{"id":626,"name":"Fonteta Sant Lluís - Dr. Waksman"},{"id":627,"name":"Fonteta Sant Lluís - Bèrnia"},{"id":628,"name":"Fonteta Sant Lluís - Algímia d'Alfara"},{"id":630,"name":"Fonteta Sant Lluís - Ebenista Caselles"},{"id":631,"name":"Fonteta Sant Lluís - Riu Sec"},{"id":632,"name":"Gravador Jordán - Alabau i Arce"},{"id":634,"name":"Gravador Jordán - Escultor Pastor"},{"id":635,"name":"Gravador Jordán - Riu Sec"},{"id":636,"name":"Fonteta Sant Lluís (impar) - Àngel Villena"},{"id":637,"name":"Fonteta Sant Lluís - Germans Maristes"},{"id":638,"name":"Ausiàs March - Algímia d'Alfara"},{"id":639,"name":"Bèrnia - Ausiàs March"},{"id":64,"name":"Vall de la Ballestera - Campanar"},{"id":640,"name":"Puigcampana - Fonteta Sant Lluís"},{"id":643,"name":"Sapadors - la Plata"},{"id":644,"name":"Sapadors - Dos d'Abril"},{"id":645,"name":"Sapadors - Sant Gregori"},{"id":649,"name":"Germans Maristes - José Durán Martínez"},{"id":650,"name":"Germans Maristes (impar) - Poliesportiu"},{"id":652,"name":"Germans Maristes (par) - Fonteta Sant Lluís"},{"id":653,"name":"Germans Maristes (par) - Poliesportiu"},{"id":654,"name":"Germans Maristes - Institut Jordi de Sant Jordi"},{"id":657,"name":"Font d'en Corts - Levantina Alegre"},{"id":658,"name":"Font d'en Corts (par) - Roig de lagarda"},{"id":659,"name":"Font d'en Corts (par) - Matador d'en Corts"},{"id":66,"name":"Punta al Mar - Camí Canal"},{"id":660,"name":"Font d'en Corts (par) - Mercavalencia"},{"id":663,"name":"el Tremolar - Crist del Refugi"},{"id":664,"name":"Crist del Refugi - del Remolí"},{"id":665,"name":"Crist del Refugi - Ctra. Del Pí"},{"id":666,"name":"Mare de Déu de Lepant (par) - Esc. F. Siurana"},{"id":668,"name":"Principal - Camí del Ribàs"},{"id":669,"name":"Ribàs (par) - Ador"},{"id":671,"name":"Font d'en Corts (impar) - Mercavalencia"},{"id":672,"name":"Font d'en Corts (impar) - Matador d'en Corts"},{"id":673,"name":"Font d'en Corts (impar) - Roig de lagarda"},{"id":674,"name":"Font d'en Corts - Casa de Roc"},{"id":679,"name":"Escultor J. Capuz (impar) - la Plata"},{"id":680,"name":"Escultor J. Capuz (impar) - Pere Aleixandre"},{"id":681,"name":"Escultor J. Capuz (impar) - Lluís Oliag"},{"id":682,"name":"Escultor J. Capuz (par) - Lluís Oliag"},{"id":683,"name":"Escultor J. Capuz (par) - Pere Aleixandre"},{"id":684,"name":"Escultor J. Capuz (par) - la Plata"},{"id":685,"name":"la Plata - Amado Granell Mesado"},{"id":686,"name":"Marqués del Túria (impar) - Cánovas"},{"id":687,"name":"Marqués del Túria - Jorge Juan"},{"id":688,"name":"Marqués del Túria - Hernán Cortés"},{"id":689,"name":"Marqués del Túria - Russafa"},{"id":690,"name":"Germanies - Castelló"},{"id":691,"name":"Espanya - Ermita"},{"id":692,"name":"Ramón i Cajal (par) - Jesús"},{"id":693,"name":"Ferran el Catòlic (par) - Àngel Guimerà"},{"id":694,"name":"Ferran el Catòlic - Juan de Mena"},{"id":695,"name":"Ferran el Catòlic (par) - Quart"},{"id":696,"name":"Ferran el Catòlic - Dr. Zamenhof"},{"id":697,"name":"Ferran el Catòlic (impar) - Quart"},{"id":698,"name":"Quart - Ferràn el Catòlic"},{"id":7,"name":"Dr. J.J.Dòmine - Port (Porta Principal)"},{"id":70,"name":"Parc Natzaret - Moraira"},{"id":700,"name":"Cid (illeta) - Tres Creus"},{"id":701,"name":"Ferran el Catòlic - Gabriel Miró"},{"id":702,"name":"Ferran el Catòlic (impar) - Àngel Guimerà"},{"id":703,"name":"Ferran el Catòlic (central) - Àngel Guimerà"},{"id":704,"name":"Ramón i Cajal - Conca"},{"id":705,"name":"Ramón i Cajal (impar) - Jesús"},{"id":706,"name":"Espanya - Sant Vicent Màrtir"},{"id":708,"name":"Germanies - Sevilla"},{"id":709,"name":"Marqués del Túria - Gregori Mayans"},{"id":710,"name":"Marqués del Túria - Mestre Gozalbo"},{"id":711,"name":"Marqués del Túria - Joaquín Costa"},{"id":712,"name":"Marqués del Túria (par) - Cánovas"},{"id":716,"name":"Cadis - Dénia"},{"id":717,"name":"Cadis - Puerto Rico"},{"id":718,"name":"Cadis - dels Centelles"},{"id":720,"name":"Mercat de Russafa"},{"id":721,"name":"Russafa - Sant Valero"},{"id":722,"name":"Regne de València - Russafa"},{"id":723,"name":"Regne de València - Lluís Santàngel"},{"id":724,"name":"Regne de València - Peris i Valero"},{"id":725,"name":"Regne de València - Mestre Gozalbo"},{"id":726,"name":"Regne de València - Gregori Mayans"},{"id":728,"name":"Pintor Salvador Abril - Mestre J. Serrano"},{"id":731,"name":"Joaquín Costa - Regne de València"},{"id":732,"name":"Ciscar - Mestre Racional"},{"id":733,"name":"Ciscar - Borriana"},{"id":734,"name":"Ciscar - Comte d'Altea"},{"id":735,"name":"Peris i Valero - Cuba"},{"id":737,"name":"Sant Vicent Màrtir - Roís de Corella"},{"id":738,"name":"Sant Vicent Màrtir - Dr. Gil i Morte"},{"id":739,"name":"Jesús - Sant Francesc de Borja"},{"id":741,"name":"Jesús - Pintor Segrelles"},{"id":742,"name":"Albacete - Mestre Sosa"},{"id":744,"name":"Conca - Bisbe Amigó"},{"id":745,"name":"Conca - Alzira"},{"id":746,"name":"Àngel Guimerà - Bon Ordre"},{"id":748,"name":"Mestre Guerrero - Joan Llorens"},{"id":749,"name":"Quart - Terol"},{"id":750,"name":"Sant Josep de la Muntanya - Pérez Galdós"},{"id":758,"name":"Aiora - Mariano Ribera"},{"id":759,"name":"Aiora - Xiva"},{"id":760,"name":"Sant Josep de Calassanç - Alberic"},{"id":761,"name":"Sant Francesc de Borja - Jesús"},{"id":764,"name":"Amèrica - Pont d'Aragó"},{"id":771,"name":"Torres dels Serrans - Comte de Trénor"},{"id":773,"name":"Poeta Llorente - Temple"},{"id":777,"name":"Amèrica - Marqués del Túria"},{"id":782,"name":"Colón - Cerdà de Tallada"},{"id":783,"name":"Els Pinazos - Colón"},{"id":784,"name":"Colón - Roger de Lloria"},{"id":785,"name":"Colón - Passeig de Russafa"},{"id":786,"name":"Xàtiva - Marqués de Sotelo"},{"id":788,"name":"Sant Agustí"},{"id":792,"name":"Encarnació - Guillem de Castro"},{"id":793,"name":"Guillem de Castro - Torres de Quart"},{"id":795,"name":"Guillem de Castro - Corona"},{"id":796,"name":"Guillem de Castro - Na Jordana"},{"id":800,"name":"Reina"},{"id":803,"name":"Quart - Guillem de Castro"},{"id":813,"name":"Av. de l'Oest - Sant Agustí"},{"id":814,"name":"Jesús - Pare Jofré"},{"id":815,"name":"Espanya - Julio Antonio"},{"id":816,"name":"Sant Vicent Màrtir - Espanya"},{"id":818,"name":"Sant Vicent Màrtir - Periodista Azzati"},{"id":819,"name":"Sant Vicent Màrtir - Cotanda"},{"id":820,"name":"Marqués de Dosaigües - Pau"},{"id":822,"name":"Pascual i Genís - Roger de Lloria"},{"id":823,"name":"Fèlix Pizcueta - Ciril Amorós"},{"id":824,"name":"Marqués de Sotelo - Sant Pau"},{"id":825,"name":"Sant Pau - Sant Agustí"},{"id":83,"name":"Eugènia Viñes - Camps"},{"id":830,"name":"Russafa - Ciril Amorós"},{"id":833,"name":"Vall de la Ballestera - Pius XII"},{"id":834,"name":"Hernàn Cortès - Ciril Amorós"},{"id":835,"name":"Marqués de Sotelo - Passatge Rex"},{"id":836,"name":"Pl. de l'Ajuntament - Ribera"},{"id":837,"name":"Pl. de l'Ajuntament - Barques"},{"id":838,"name":"Pl. de l'Ajuntament - Font"},{"id":84,"name":"Eugènia Viñes - Francesc Miralles"},{"id":840,"name":"Pl. de l'Ajuntament - Cotanda"},{"id":843,"name":"Pl. de l'Ajuntament - Ateneu"},{"id":844,"name":"Av. de l'Oest - Garrigues"},{"id":845,"name":"Periodista Azzati - Arquebisbe Mayoral"},{"id":846,"name":"Roger de Lloria - Colón"},{"id":847,"name":"Correus - Pascual i Genís"},{"id":848,"name":"Pintor Sorolla - A. Magnànim"},{"id":849,"name":"Font d'en Corts (par) - Mossén Palanca"},{"id":850,"name":"Font d'en Corts - Camí dels Rocs"},{"id":855,"name":"Orxata - Mestre Serrano"},{"id":866,"name":"Catalunya - Santa Cruz de la Zarza"},{"id":867,"name":"Clariano - Palància"},{"id":868,"name":"Clariano - Albalat dels Tarongers"},{"id":869,"name":"Amadeu de Savoia - Suècia"},{"id":870,"name":"Misser Mascó - Dr. Rodríguez Fornós"},{"id":871,"name":"Misser Mascó - Dr. Moliner"},{"id":872,"name":"Misser Mascó - Montfort"},{"id":874,"name":"Finlàndia - General Gil Dolz"},{"id":880,"name":"Pintor Salvador Abril - Maties Perelló"},{"id":882,"name":"Fonteta Sant Lluís (par) - Àngel Villena"},{"id":886,"name":"Peris i Valero - Pintor Salvador Abril"},{"id":892,"name":"la Plata - Poeta Miguel Hernández"},{"id":9,"name":"Dr. Lluch - Vicent Gallart"},{"id":904,"name":"Glòria (par) - Oliveral"},{"id":906,"name":"Karl Marx - Guadalquivir"},{"id":907,"name":"Guadalquivir - Karl Marx"},{"id":910,"name":"Glòria (impar) - Oliveral"},{"id":911,"name":"Camí de les Vaques (impar)"},{"id":912,"name":"Camí de les Vaques (par)"},{"id":921,"name":"Carrera del Riu - Entrada Sanques"},{"id":922,"name":"Carrera del Riu - Camí dels Anouers"},{"id":923,"name":"Carrera del Riu (par) - Canal"},{"id":924,"name":"Carrera del Riu - Trav. Pinedo a la Mar"},{"id":928,"name":"Carrera del Riu - Mossén Cuenca"},{"id":929,"name":"Carrera del Riu (impar) - Canal"},{"id":930,"name":"el Tremolar - Camí Racó"},{"id":931,"name":"el Tremolar - Guadiana"},{"id":932,"name":"el Tremolar - Barraca de Troia"},{"id":933,"name":"el Tremolar - Casa Rabot"},{"id":934,"name":"el Tremolar - Camí del Cavalló"},{"id":935,"name":"el Tremolar - Cases Grill"},{"id":936,"name":"el Tremolar - Séquia de l'Or"},{"id":937,"name":"el Tremolar - Font d'en Corts"},{"id":938,"name":"el Tremolar - Camí del Bracet"},{"id":939,"name":"Carrera del Riu - Entrada casa Rosquilla"},{"id":940,"name":"Carrera del Riu - Casa Andrés"},{"id":948,"name":"Corts Valencianes - Cervantes"},{"id":949,"name":"Cases de Bàrcena I"},{"id":950,"name":"Cases de Bàrcena II"},{"id":951,"name":"Cases de Bàrcena III"},{"id":953,"name":"Cases de Bàrcena IV"},{"id":954,"name":"Cases de Bàrcena V"},{"id":955,"name":"Cases de Bàrcena VI"},{"id":956,"name":"Corts Valencianes - Marià Benlliure"},{"id":958,"name":"Dr. Peset Aleixandre - Mondúver"},{"id":961,"name":"Jaime Beltrán - Misser Rabassa"},{"id":965,"name":"Germans Villalonga - Enric Navarro"},{"id":966,"name":"Germans Villalonga - Dr. Vicent Zaragozà"},{"id":967,"name":"Ramón Asensio - Guàrdia Civil"},{"id":972,"name":"Uruguai - Misser Rabassa"},{"id":974,"name":"Carters - Llanera de Ranes"},{"id":975,"name":"Carters - Calvo Acacio"},{"id":976,"name":"Carters (impar) - Primer de Maig"},{"id":978,"name":"Carters (par) - Primer de Maig"},{"id":979,"name":"Carters - Mossén Febrer"},{"id":983,"name":"Ramón i Cajal - Bailén"},{"id":984,"name":"Periodista Azzati - Convent de Sant Francesc"},{"id":985,"name":"Jaume Esteve Cubells - Dr. Vicent Zaragozà"},{"id":987,"name":"Mistral - Murta"}]